{"E7ffRsM/ecWYY1jVsfS73w==":"thumb-1920-436837-1920x1080.jpg","NelEI1nEZmf31qKWuQSRUw==":"blue_gears-1920x1080.jpg","/hvVd/EJBKKBuCbkR7XVfw==":"test_strategy-768x512.jpg","uISJHEKyuYJo9jXflxRmxA==":"and_testing_lives-1600x750.jpg","S/JBCNjAfhIBV+tqQ8//AQ==":"test_typology-1883x1393.png","EHKy7V0Y+A1gGPpG3CoGHw==":"system_under_test_en-1064x1186.png","LUVBQH/TZPIdPVW/DzxaHg==":"typological_model_of_tests-1090x762.png","sumvbNYx2ibqK0Tr1FAP/Q==":"test_targets-1066x628.png","CSFrMdYgVx9FSe2FZlSWUQ==":"manual_tooled_automated-1094x842.png","T+c0IL4KP4qVeNMR5lN05g==":"testing_positive_negative_synthetic_analytical-1928x1930.png","BSVQ4qtYkFdCS5+KIv7cxA==":"agile_testing_quadrants-1614x1374.png","dE3Wy0oU9MglCsr2U7g3iw==":"periodic_classification_of_software_testing-2506x1347.png","nmqHwIjYWYX1DUHAdJlc2Q==":"box_black_gray_white-754x752.png","Yh4iSPwLJ1VilUWBPmwOOw==":"box_black_gray_white-754x794.png","Jm9uRN6Q8I3ov1h7eQkX5A==":"test_targets-1066x1126.png","OqRpryhqk/AMRLtfocElgQ==":"testing_positive_negative_synthetic_analytical-1928x1930.png","BIB+I176ILV1e8iNOcsJ9A==":"manual_tooled_automated-1094x842.png","qA1pA9kdharsMkoHUP/LLg==":"maturity_levels_of_testing-2374x2004.png","TsG9kQxp3c4sl2CieREzjw==":"test_correcting-1776x899.png","KVT9uYdPvgQ6dDtycDWgHg==":"test_correcting-1-1776x899.png","jGdyFTMmolvxgvMy2vuR3A==":"biohazard-1920x1280.jpg","HUW8Ws7EApOI8/ShgKpY4g==":"biohazard-1-1920x1280.jpg","MHlKbc3ZYSs/khfVAST+1g==":"biohazard-2-1920x1280.jpg","a1n8kw7gTpnxViUsON0qQg==":"biohazard-3-1920x1280.jpg","9j6V1SdPCgUcizVUAA0mVQ==":"mbr-720x1080.jpg","iAWdreo3AvlvXiJdcX/C4w==":"biohazard_minimalism-1920x1080.jpg","urz1xAngx/yAoSkVxnL/Ug==":"digitalart-1532786402395-1383-1920x1200.jpg"}